Workbook

Sheet 功能进度表
A1: 序号 | B1: 所属页面 | C1: 功能模块 | D1: 具体功能点 | E1: 功能与交互说明（正向 + 异常场景） | F1: 预计完成日期 | G1: 实际开始日期 | H1: 实际完成日期 | I1: 历时（天） | J1: 协同经办人 | K1: 进度状态 | L1: 备注 / 延期说明
A2: 1 | B2: 登录页 | C2: 登录方式区 | D2: 1. 微信扫描登录 2. 手机验证码登录 3. 密码登录 | E2: 1. 支持微信扫描登录、手机验证码登录、密码登录。 2. 登录前需勾选用户协议与隐私协议。 3. 首次同意后，后台记录首次同意时间。 异常：1. 验证码输入错误时，就地提示错误原因，并支持重新输入或重新获取验证码。 2. 登录请求失败或服务不可用时，提示检查网络后重试。 3. 微信扫码二维码过期时，提示刷新二维码后继续登录。 | F2: 46226 | G2: 46226 | H2: 46227 | I2: =IF(OR(G2="",H2="",H2<G2),"",_xlfn.NETWORKDAYS.INTL(G2,H2,1,填写说明!$D$2:$D$200)) -> 2
A3: 2 | B3: Tokens 管理页 | C3: 页顶部全局信息栏 | D3: 1. AI 工具配置教程入口 2. 今日剩余次数查询 3. 可使用余额查询 | E3: 1. 点击【AI 工具配置教程】进入操作指引，查看安装与配置步骤。 2. 鼠标悬浮在【今日剩余次数】【可使用余额】旁问号上，显示字段说明。 3. 实时展示当前账号剩余调用次数和可用余额。 异常： 1.未登录时仍可看说明文案，但余额和次数不展示真实数据。 | F3: 46227 | G3: 46227 | H3: 46229 | I3: =IF(OR(G3="",H3="",H3<G3),"",_xlfn.NETWORKDAYS.INTL(G3,H3,1,填写说明!$D$2:$D$200)) -> 1
A4: 3 | B4: Tokens 管理页 | C4: 左侧侧边导航栏 | D4: 1. 菜单页面切换 2. 个人中心入口 3. 登录 / 注册入口 | E4: 1. 点击左侧菜单完成页面切换。 1.1 点击【Tokens 管理】进入 Tokens 管理页。 1.2 点击【AI工具管理】进入 AI 工具管理页。 1.3 点击【模型供应商】进入模型供应商页。 1.4 点击【订阅 / 充值】进入订阅 / 充值页。 1.5 点击【订单中心】进入订单中心页。 2. 点击左下角【个人中心】进入账号资料页。 3. 未登录状态点击【登录 / 注册】进入账号体系。 异常： 1. 未登录访问受限页面时先弹出登录提示。 2. 登录入口无响应时提示检查网络后重试。 | F4: 46228 | G4: 46228 | H4: 46229 | I4: =IF(OR(G4="",H4="",H4<G4),"",_xlfn.NETWORKDAYS.INTL(G4,H4,1,填写说明!$D$2:$D$200)) -> 0
A5: 4 | B5: Tokens 管理页 | C5: AI 模型卡片区 | D5: 1. 六张模型卡片基础信息展示 2. 主用模型与上次使用时间展示 | E5: 1. 展示 6 张 AI 工具卡片。Codex、 Claude、OpenCode、 Gemini CLI、OpenClaw、Hermes； 2. 每张卡片展示基础状态信息。 2.1 模型名称 2.2 主用模型 2.3 上次使用时间 3. 用户下载安装 WeTokens 后，系统检测电脑上各 AI 工具的安装状态。 3.1 已安装工具显示【打开启用】按钮 3.2 未安装工具显示【下载安装】按钮 异常： 1. 最近使用时间缺失时显示【未使用】。 2. 主模型为空或未获取到数据时显示【--】。 | F5: 46297 | G5: 46297 | H5: 46297 | I5: =IF(OR(G5="",H5="",H5<G5),"",_xlfn.NETWORKDAYS.INTL(G5,H5,1,填写说明!$D$2:$D$200)) -> 1
A6: 5 | B6: Tokens 管理页 | D6: 1. AI 工具安装状态检测 2. AI 工具下载安装 / 打开启用 3. 模型可用性检测与引导 | E6: 1. 用户下载安装 WeTokens 后，系统检测电脑上是否已安装对应 AI 工具；已安装工具按钮更新为【打开启用】，未安装工具显示【下载安装】。 2. 点击【下载安装】后执行工具下载与安装，安装完成后按钮状态更新为【打开启用】。 3. 点击【打开启用】时，系统检测当前工具是否已有可用模型；未配置时引导前往订阅 / 充值或配置模型，已配置时提示可直接使用。 异常： 1. 安装失败时明确提示失败原因，并支持重新下载安装或查看安装帮助。 2. 检测到快捷方式存在但本地执行文件缺失时，提示安装文件异常，并支持重新安装。 3. 工具已打开但没有可用模型时，引导前往订阅 / 充值或配置模型。 4. 检测到已有可用模型时，提示可直接录入 API Key 并继续接入平台。 | F6: 46298 | G6: 46298 | H6: 46298 | I6: =IF(OR(G6="",H6="",H6<G6),"",_xlfn.NETWORKDAYS.INTL(G6,H6,1,填写说明!$D$2:$D$200)) -> 0
A7: 7 | B7: Tokens 管理页 | C7: 下方数据总览区 | D7: 1. 工具使用统计卡片 2. 工具维度汇总展示 | E7: 1. 登录后展示工具使用统计卡片，按工具查看使用概况。 2. 可看到不同工具当前使用状态、活跃情况或聚合统计。 异常：1. 无使用数据时显示空状态说明。 2. 数据接口超时或失败时展示加载失败提示。 | F7: 46300 | G7: 46300 | H7: 46300 | I7: =IF(OR(G7="",H7="",H7<G7),"",_xlfn.NETWORKDAYS.INTL(G7,H7,1,填写说明!$D$2:$D$200)) -> 1
A8: 8 | B8: Tokens 管理页 | C8: 用量趋势分析区 | D8: 1. 总览 / 消耗明细切换 2. 时间范围切换 | E8: 1. 支持切换数据视图。 1.1 点击【总览】查看整体tokens消耗概况。 1.2 点击【供应商】查看供应商的tokens消耗概况。 1.3 点击【消耗明细】查看明细记录，按照模型名称维度来统计； 2. 支持切换时间范围。今天、近 7 天、近 30 天、自定义选择时间范围； 3. 展示统计结果。 Tokens 合计、趋势图、汇总信息 异常： 1. 切换后没有匹配数据时显示空结果。 2. 图表加载失败时提示刷新重试。 3. 时间范围切换异常时保留当前已加载内容。 | F8: 46301 | G8: 46301 | H8: 46301 | I8: =IF(OR(G8="",H8="",H8<G8),"",_xlfn.NETWORKDAYS.INTL(G8,H8,1,填写说明!$D$2:$D$200)) -> 1
A9: 9 | B9: AI工具管理页 | C9: 左侧工具列表区 | D9: 1. 工具列表展示 2. 工具焦点切换 3.本地代理 开启/关闭功能 4.更换模型 5.检测通道 6.启用/切换供应商 | E9: 1. 展示平台支持的 AI 工具列表。Codex、 Claude、OpenCode、 Gemini CLI、OpenClaw、Hermes； 2. 显示工具版本，桌面版or cli、工具版本号、和工具简介； 3.默认开启本地代理，关闭时弹窗提醒“关闭后，请求将不再经由 CC Switch 转发，直接连接供应商。” 4.无新增外部供应商时，显示【去添加供应商】按钮，单击跳转到【模型供应商】页面，并弹【添加供应商】弹窗页面； 5.更换模型：在ai工具管理页中，可对单个工具进行模型配置，claude使用映射模型配置弹窗，其他工具用普通模型配置弹窗；配置成功需要给 toast提示【已保存“工具名称”的x个模型】 6.检测：用户点击检测，系统请求平台接口测试连通、统计请求耗时；连通正常弹出提示【连接正常 (耗时数值 ms)】 7.启用/使用中：用户点击启，启用成提示【重启当前 AI 工具后即可生效 已切换至 Google AI，连接正常 (1631ms)】，启用失败需提示失败原因； 异常： 1.检测：用户点击检测 1.1接口无法连通：提示连接失败，校验不通过，通道不可用； 1.2.请求超时：提示检测超时需重试； 1.3Key 失效时：提示连接异常请重新配置供应商。 | F9: 46302 | G9: 46302 | H9: 46302 | I9: =IF(OR(G9="",H9="",H9<G9),"",_xlfn.NETWORKDAYS.INTL(G9,H9,1,填写说明!$D$2:$D$200)) -> 1
A10: 12 | B10: 模型供应商页 | C10: 已接入供应商列表区 | D10: 1. 供应商连接信息展示 2. 配置入口展示 | E10: 1. 展示已接入供应商名称、连接状态、已启用模型数量。 2. 提供查看配置、修改配置等入口。 3. 启用供应商成功后，展示启用结果与检测反馈，并提示重启当前 AI 工具后生效。 异常： 1. 供应商余额小于等于10元时，，提示【当前余额不足 10 元 当前余额不足 10 元，继续使用可能导致模型请求失败。】 按钮：我知道了 去订阅/充值 | F10: 46305 | G10: 46305 | H10: 46305 | I10: =IF(OR(G10="",H10="",H10<G10),"",_xlfn.NETWORKDAYS.INTL(G10,H10,1,填写说明!$D$2:$D$200)) -> 0
A11: 13 | B11: 模型供应商页 | C11: 添加供应商入口 | D11: 添加供应商按钮 | E11: 1. 点击【添加供应商】打开新增供应商流程。详细信息和交互看原型； 异常： 1. 未登录点击时先弹出登录提示。 | F11: 46306 | G11: 46306 | H11: 46306 | I11: =IF(OR(G11="",H11="",H11<G11),"",_xlfn.NETWORKDAYS.INTL(G11,H11,1,填写说明!$D$2:$D$200)) -> 0
A12: 14 | B12: 添加供应商弹窗 | C12: Step1 基础信息填写区 | D12: 1. 供应商名称、备注、官网地址 2. 请求地址与 API Key | E12: 1. 支持两种新增方式。 1.1 选择预设供应商模板 1.2 自定义录入供应商信息 2. 填写基础配置项。 2.1 供应商名称 2.2 备注 2.3 官网地址 2.4 请求地址 2.5 API Key 3. 点击【验证并拉取模型】进入下一步。 异常：1. 供应商名称或 API Key 为空时禁止下一步。 2. 请求地址格式错误时提示修正。 3. Key 校验失败时保留已填内容，便于修改后重试。 | F12: 46307 | G12: 46307 | H12: 46307 | I12: =IF(OR(G12="",H12="",H12<G12),"",_xlfn.NETWORKDAYS.INTL(G12,H12,1,填写说明!$D$2:$D$200)) -> 1
A13: 15 | B13: 添加供应商弹窗 | C13: Step2 模型选择区 | D13: 1. 模型拉取结果展示 2. 启用模型勾选 | E13: 1. 验证成功后展示模型结果。系统默认填充4个模型，用户可以更换； 2.保存后改供应商配置将同步至所有AI工具中； 异常： 1. 拉取模型失败时提示【模型拉取失败，请重新验证或检查供应商配置。】 | F13: 46308 | G13: 46308 | H13: 46308 | I13: =IF(OR(G13="",H13="",H13<G13),"",_xlfn.NETWORKDAYS.INTL(G13,H13,1,填写说明!$D$2:$D$200)) -> 1
A14: 17 | B14: 订阅 / 充值页 | C14: 顶部切换栏 | D14: 1. 订阅制 Tab 2. 按量充值 Tab 3. 订单记录入口 | E14: 1. 点击【订阅制】【按量充值】切换购买模式。 2. 点击【订单记录】进入订单列表页。 异常：1. Tab 切换失败时保留当前内容并提示重试。 2. 未登录访问订单记录时先弹登录提示。 | F14: 46310 | G14: 46310 | H14: 46310 | I14: =IF(OR(G14="",H14="",H14<G14),"",_xlfn.NETWORKDAYS.INTL(G14,H14,1,填写说明!$D$2:$D$200)) -> 1
A15: 18 | B15: 订阅 / 充值页 | C15: 订阅套餐选择区 | D15: 1. Lite / Pro / Pro Plus / Ultra 套餐选择 2. 套餐信息展示 | E15: 1. 展示套餐核心信息。 1.1 套餐价格 1.2 有效期 1.3 每日次数 1.4 身份徽章 2. 点击不同套餐后，右侧支付区同步更新已选套餐和价格。 异常：1. 未选中任何套餐时不能直接支付。 2. 套餐信息异常时提示刷新后重试。 | F15: 46311 | G15: 46311 | H15: 46311 | I15: =IF(OR(G15="",H15="",H15<G15),"",_xlfn.NETWORKDAYS.INTL(G15,H15,1,填写说明!$D$2:$D$200)) -> 1
A16: 19 | B16: 订阅 / 充值页 | C16: 订阅规则说明区 | D16: 1. 规则文案展示 2. 退款示例展开 3. 订阅计量表展开 | E16: 1. 展示订阅规则说明。 1.1 有效期 1.2 次日清零 1.3 余额兜底 1.4 退款规则 2. 点击【查看示例】展开退款计算说明。 3. 点击【查看详细计费档位与可用模型】展开订阅计量表。 异常：1. 展开内容加载失败时提示稍后重试。 2. 数据缺失时至少保留基础规则文案。 | F16: 46312 | G16: 46312 | H16: 46312 | I16: =IF(OR(G16="",H16="",H16<G16),"",_xlfn.NETWORKDAYS.INTL(G16,H16,1,填写说明!$D$2:$D$200)) -> 0
A17: 20 | B17: 订阅 / 充值页 | C17: 订阅支付区 | D17: 1. 微信 / 支付宝切换 2. 二维码支付 3. 自动续费开关 | E17: 1. 支持切换支付方式。 1.1 微信支付 1.2 支付宝 2. 展示支付信息。 2.1 已选套餐 2.2 应付金额 2.3 二维码 3. 支持开启或关闭自动续费。 异常：1. 订单创建失败、支付超时、渠道异常或用户主动取消时，统一提示支付未完成，并支持重新支付。 2. 支持跳转订单中心查看状态，避免重复扣费疑虑。 | F17: 46313 | G17: 46313 | H17: 46313 | I17: =IF(OR(G17="",H17="",H17<G17),"",_xlfn.NETWORKDAYS.INTL(G17,H17,1,填写说明!$D$2:$D$200)) -> 0
A18: 21 | B18: 订阅 / 充值页 | C18: 按量充值套餐区 | D18: 1. 充值档位选择 2. 到账余额展示 | E18: 1. 支持选择充值档位。 1.1 50 元 1.2 100 元 1.3 500 元 2. 展示充值结果说明。 2.1 到账余额 2.2 赠送金额 2.3 计费说明 异常：1. 充值档位未选中时不可继续支付。 2. 价格配置异常时提示刷新。 | F18: 46314 | G18: 46314 | H18: 46314 | I18: =IF(OR(G18="",H18="",H18<G18),"",_xlfn.NETWORKDAYS.INTL(G18,H18,1,填写说明!$D$2:$D$200)) -> 1
... A37: 41 | B37: 卸载页 | C37: 工具卸载确认与结果反馈 | D37: 1. 卸载风险提醒 2. 保留配置选择 3. 二次确认卸载 4. 卸载完成反馈 | E37: 1. 用户在已安装工具上发起卸载时，先展示将移除本地客户端，但可选择保留平台配置和模型映射。 2. 二次确认后执行卸载，完成后更新工具状态为【未安装】，并保留重新安装入口。 3. 卸载完成后提示本次结果、剩余配置状态和重新安装指引。 异常：1. 卸载过程中断时保留原安装状态，并提示用户稍后重试。 2. 本地进程仍在运行时禁止直接卸载，需先关闭对应工具。 3. 卸载失败但部分文件已删除时，应提示修复建议，避免状态显示错误。 | F37: 46334 | G37: 46334 | H37: 46334 | I37: =IF(OR(G37="",H37="",H37<G37),"",_xlfn.NETWORKDAYS.INTL(G37,H37,1,填写说明!$D$2:$D$200)) -> 0

Sheet 填写说明
A1: 项目 | B1: 说明 | D1: 节假日日期 | E1: 说明
A2: 表格用途 | B2: 用于按功能点跟踪整体交付进度，只看统一起止时间和结果状态，不拆研发内部个人工时。 | E2: 在 D 列从第 2 行开始填写需要排除的节假日日期；历时（天）会自动排除周六、周日以及这里维护的日期。
A3: 计划开始日期 | B3: 该功能统一启动时间，由技术团队内部自行协调前后端或客户端开工顺序。
A4: 计划整体交付截止日 | B4: 前端、后端、客户端共同确认的最终交付时间，只填一个统一日期。
A5: 实际完成日期 | B5: 全部自测、联调完成并可视为真实落地后的日期。通常在状态变更为已上线时填写。
A6: 进度状态 | B6: 固定口径：待评估 / 未开始 / 开发中 / 自测完成 / 已提测 / 已上线 / 延期调整。
A7: 状态定义 | B7: 待评估：方案或工期未确认。未开始：已确认要做但未开工。开发中：研发或联调进行中。自测完成：研发已完成自测。已提测：已提交测试。已上线：正式发布完成。延期调整：确认无法按原截止日交付。
A8: 备注 / 延期说明 | B8: 按期交付可留空。若预判延期，必须提前填写，推荐格式：延期原因｜影响说明｜新预估交付时间。
A9: 延期原因分类 | B9: 可选分类：跨项目挤占工时 / 技术卡点 / 外部依赖 / 需求微调。
A10: 执行建议 | B10: 建议周会前统一更新一次；如果预计无法按截止日完成，应立即将状态调整为延期调整并同步新时间。
A11: 是否扩展字段 | B11: 如果你后续确实需要更细管理，可以追加负责人字段；当前模板先按核心管理字段落地。
